asciichartpy/__init__.py
asciichartpy-1.5.24.dist-info/LICENSE.txt
asciichartpy-1.5.24.dist-info/METADATA
asciichartpy-1.5.24.dist-info/WHEEL
asciichartpy-1.5.24.dist-info/top_level.txt
asciichartpy-1.5.24.dist-info/RECORD
