Metadata-Version: 2.1
Name: asciichartpy
Version: 1.5.24
Summary: Nice-looking lightweight console ASCII line charts ╭┈╯ with no dependencies
Home-page: https://github.com/kroitor/asciichart
Author: Igor Kroitor
Author-email: igor.kroitor@gmail.com
License: MIT
Keywords: asciichart,ascii,chart,charting,charts,console,terminal,draw,box-drawing,box drawing,drawing,stats,line,linear,plot,graph,ascii graphics,graphics,command line,commandline,bash,shell,sh,light
Platform: UNKNOWN
Classifier: Development Status :: 4 - Beta
Classifier: Intended Audience :: Developers
Classifier: Intended Audience :: Financial and Insurance Industry
Classifier: Intended Audience :: Information Technology
Classifier: Topic :: Software Development :: Build Tools
Classifier: Topic :: Office/Business :: Financial :: Investment
Classifier: License :: OSI Approved :: MIT License
Classifier: Programming Language :: Python :: 2
Classifier: Programming Language :: Python :: 2.7
Classifier: Programming Language :: Python :: 3
Classifier: Programming Language :: Python :: 3.3
Classifier: Programming Language :: Python :: 3.4
Classifier: Programming Language :: Python :: 3.5
Classifier: Programming Language :: Python :: 3.6
Classifier: Programming Language :: JavaScript
Classifier: Programming Language :: PHP
Classifier: Operating System :: OS Independent
Classifier: Environment :: Console
Requires-Dist: setuptools
Provides-Extra: qa
Requires-Dist: flake8 ; extra == 'qa'
